Metadata-Version: 2.1
Name: miservice2
Version: 2021.7.25
Summary: XiaoMi Cloud Service
Home-page: https://github.com/Yonsm/MiService
Author: Yonsm
Author-email: Yonsm@qq.com
License: MIT
Platform: UNKNOWN
Classifier: Programming Language :: Python :: 3
Classifier: License :: OSI Approved :: MIT License
Classifier: Operating System :: OS Independent
Requires-Python: >=3.7
